hxb_mcp_demo/__init__.py
hxb_mcp_demo-0.1.4.dist-info/METADATA
hxb_mcp_demo-0.1.4.dist-info/WHEEL
hxb_mcp_demo-0.1.4.dist-info/entry_points.txt
hxb_mcp_demo-0.1.4.dist-info/RECORD
