Metadata-Version: 2.4
Name: hxb-mcp-demo
Version: 0.1.4
Summary: Add your description here
Author-email: 侯晓宝 <xiaobaoword@163.com>
Requires-Python: >=3.13
Requires-Dist: mcp[cli]>=1.10.1
